juniperSNMPv3crypt/__init__.py
juniperSNMPv3crypt/crypt9.py
juniperSNMPv3crypt/snmpv3_hash.py
juniperSNMPv3crypt-0.0.5.dist-info/LICENSE
juniperSNMPv3crypt-0.0.5.dist-info/METADATA
juniperSNMPv3crypt-0.0.5.dist-info/WHEEL
juniperSNMPv3crypt-0.0.5.dist-info/top_level.txt
juniperSNMPv3crypt-0.0.5.dist-info/RECORD
