Metadata-Version: 2.1
Name: juniperSNMPv3crypt
Version: 0.0.5
Summary: Encrypt/decrypts juniper $9$ secrets
Home-page: https://github.com/zach-bray/junipercrypt
Author: Zach Bray
Author-email: zachbray123@gmail.com
License: UNKNOWN
Platform: UNKNOWN
Classifier: Programming Language :: Python
Classifier: License :: OSI Approved :: MIT License
Classifier: Operating System :: OS Independent
